brewblox_service/__init__.py
brewblox_service/features.py
brewblox_service/http.py
brewblox_service/middlewares.py
brewblox_service/models.py
brewblox_service/mqtt.py
brewblox_service/repeater.py
brewblox_service/scheduler.py
brewblox_service/service.py
brewblox_service/testing.py
brewblox_service-3.3.2.dist-info/LICENSE.md
brewblox_service-3.3.2.dist-info/METADATA
brewblox_service-3.3.2.dist-info/WHEEL
brewblox_service-3.3.2.dist-info/RECORD
