Metadata-Version: 2.1
Name: brewblox-service
Version: 3.3.2
Summary: Scaffolding for Brewblox backend services
License: GPL-3.0
Author: BrewPi
Author-email: development@brewpi.com
Requires-Python: >=3.9,<4
Classifier: License :: OSI Approved :: GNU General Public License v3 (GPLv3)
Classifier: Programming Language :: Python :: 3
Classifier: Programming Language :: Python :: 3.9
Classifier: Programming Language :: Python :: 3.10
Classifier: Programming Language :: Python :: 3.11
Requires-Dist: aiohttp (==3.*)
Requires-Dist: aiohttp-pydantic (==1.*)
Requires-Dist: aiomqtt (==1.*)
Requires-Dist: pydantic (==1.*)
